setup.py
clicker_server.egg-info/PKG-INFO
clicker_server.egg-info/SOURCES.txt
clicker_server.egg-info/dependency_links.txt
clicker_server.egg-info/not-zip-safe
clicker_server.egg-info/requires.txt
clicker_server.egg-info/top_level.txt
server/__init__.py
server/text.py