Metadata-Version: 1.0
Name: clicker-server
Version: 0.1
Summary: Clicker Server
Home-page: http://github.com/ftes/clicker
Author: Fredrik Teschke
Author-email: f@ftes.de
License: UNKNOWN
Platform: UNKNOWN
